django_nanoid_integration/__init__.py
django_nanoid_integration/alphabets.py
django_nanoid_integration/fields.py
django_nanoid_integration/helpers.py
django_nanoid_integration/mixins.py
django_nanoid_integration/upload.py
tests/__init__.py
django_nanoid_integration-0.1.0.dist-info/LICENSE
django_nanoid_integration-0.1.0.dist-info/METADATA
django_nanoid_integration-0.1.0.dist-info/WHEEL
django_nanoid_integration-0.1.0.dist-info/top_level.txt
django_nanoid_integration-0.1.0.dist-info/RECORD
