Metadata-Version: 2.1
Name: django-nanoid-integration
Version: 0.1.0
Summary: Save your Django uploaded files using NanoIDs for file names or store them in directories named with NanoIDs.
Home-page: https://github.com/spechtx/django-nanoid-integration
Author: Christian H. Specht
Author-email: cs@spechtx.de
License: MIT
Classifier: Programming Language :: Python :: 3
Classifier: License :: OSI Approved :: MIT License
Classifier: Operating System :: OS Independent
Requires-Python: >=3.6
License-File: LICENSE
Requires-Dist: Django >=1.7
Requires-Dist: nanoid
